odoo/addons/sale_coupon_portal/README.rst
odoo/addons/sale_coupon_portal/__init__.py
odoo/addons/sale_coupon_portal/__manifest__.py
odoo/addons/sale_coupon_portal/controllers/__init__.py
odoo/addons/sale_coupon_portal/controllers/portal.py
odoo/addons/sale_coupon_portal/i18n/es.po
odoo/addons/sale_coupon_portal/i18n/sale_coupon_portal.pot
odoo/addons/sale_coupon_portal/readme/CONFIGURE.rst
odoo/addons/sale_coupon_portal/readme/CONTRIBUTORS.rst
odoo/addons/sale_coupon_portal/readme/DESCRIPTION.rst
odoo/addons/sale_coupon_portal/readme/USAGE.rst
odoo/addons/sale_coupon_portal/static/description/icon.svg
odoo/addons/sale_coupon_portal/static/description/index.html
odoo/addons/sale_coupon_portal/static/src/js/tour_coupon_portal.js
odoo/addons/sale_coupon_portal/templates/assets.xml
odoo/addons/sale_coupon_portal/templates/coupon_portal_templates.xml
odoo/addons/sale_coupon_portal/tests/__init__.py
odoo/addons/sale_coupon_portal/tests/test_sale_coupon_portal.py
odoo13_addon_sale_coupon_portal-13.0.1.0.1.dev4.dist-info/METADATA
odoo13_addon_sale_coupon_portal-13.0.1.0.1.dev4.dist-info/WHEEL
odoo13_addon_sale_coupon_portal-13.0.1.0.1.dev4.dist-info/top_level.txt
odoo13_addon_sale_coupon_portal-13.0.1.0.1.dev4.dist-info/RECORD
